pymelcloudhome/__init__.py
pymelcloudhome/client.py
pymelcloudhome/config.py
pymelcloudhome/errors.py
pymelcloudhome/models/__init__.py
pymelcloudhome/models/base.py
pymelcloudhome/models/building.py
pymelcloudhome/models/device.py
pymelcloudhome/models/user.py
pymelcloudhome/services/__init__.py
pymelcloudhome/services/api_client.py
pymelcloudhome/services/authentication.py
pymelcloudhome/services/cache.py
pymelcloudhome/services/device_service.py
pymelcloudhome-0.2.0.dist-info/METADATA
pymelcloudhome-0.2.0.dist-info/WHEEL
pymelcloudhome-0.2.0.dist-info/licenses/LICENSE
pymelcloudhome-0.2.0.dist-info/RECORD
