Metadata-Version: 2.4
Name: pymelcloudhome
Version: 0.2.0
Summary: A modern, fully asynchronous Python library for the Mitsubishi Electric MelCloudHome platform.
License: MIT
License-File: LICENSE
Keywords: melcloudhome,mitsubishi,hvac,api,asyncio
Author: Martin Hultman
Author-email: martin@hultman.dev
Requires-Python: >=3.10
Classifier: Development Status :: 4 - Beta
Classifier: Intended Audience :: Developers
Classifier: License :: OSI Approved :: MIT License
Classifier: Programming Language :: Python :: 3
Classifier: Programming Language :: Python :: 3.10
Classifier: Programming Language :: Python :: 3.11
Classifier: Programming Language :: Python :: 3.12
Classifier: Topic :: Home Automation
Classifier: Topic :: Software Development :: Libraries :: Python Modules
Requires-Dist: aiohttp (>=3.9.5)
Requires-Dist: beautifulsoup4 (>=4.12.3)
Requires-Dist: playwright (>=1.44.0)
Requires-Dist: pydantic (>=2.7.1)
Requires-Dist: yarl (>=1.9.4)
Project-URL: Homepage, https://github.com/MHultman/pymelcloudhome
Project-URL: Repository, https://github.com/MHultman/pymelcloudhome
